classyplugins.py
setup.py
classyplugins.egg-info/PKG-INFO
classyplugins.egg-info/SOURCES.txt
classyplugins.egg-info/dependency_links.txt
classyplugins.egg-info/top_level.txt