Metadata-Version: 1.1
Name: classyplugins
Version: 0.0.5
Summary: Lightweight class-based plugin system
Home-page: http://code.google.com/p/classyplugins/
Author: Jacob Brunson
Author-email: classyplugins@jacobbrunson.com
License: LGPL
Platform: UNKNOWN
Classifier: Programming Language :: Python
Classifier: Topic :: Software Development :: Libraries :: Application Frameworks
